iricore/__init__.py
iricore/config.py
iricore/data/ccir/ccir11.asc
iricore/data/ccir/ccir12.asc
iricore/data/ccir/ccir13.asc
iricore/data/ccir/ccir14.asc
iricore/data/ccir/ccir15.asc
iricore/data/ccir/ccir16.asc
iricore/data/ccir/ccir17.asc
iricore/data/ccir/ccir18.asc
iricore/data/ccir/ccir19.asc
iricore/data/ccir/ccir20.asc
iricore/data/ccir/ccir21.asc
iricore/data/ccir/ccir22.asc
iricore/data/igrf/dgrf1945.dat
iricore/data/igrf/dgrf1950.dat
iricore/data/igrf/dgrf1955.dat
iricore/data/igrf/dgrf1960.dat
iricore/data/igrf/dgrf1965.dat
iricore/data/igrf/dgrf1970.dat
iricore/data/igrf/dgrf1975.dat
iricore/data/igrf/dgrf1980.dat
iricore/data/igrf/dgrf1985.dat
iricore/data/igrf/dgrf1990.dat
iricore/data/igrf/dgrf1995.dat
iricore/data/igrf/dgrf2000.dat
iricore/data/igrf/dgrf2005.dat
iricore/data/igrf/dgrf2010.dat
iricore/data/igrf/dgrf2015.dat
iricore/data/igrf/igrf2020.dat
iricore/data/igrf/igrf2020s.dat
iricore/data/index/apf107.dat
iricore/data/index/ig_rz.dat
iricore/data/mcsat/mcsat11.dat
iricore/data/mcsat/mcsat12.dat
iricore/data/mcsat/mcsat13.dat
iricore/data/mcsat/mcsat14.dat
iricore/data/mcsat/mcsat15.dat
iricore/data/mcsat/mcsat16.dat
iricore/data/mcsat/mcsat17.dat
iricore/data/mcsat/mcsat18.dat
iricore/data/mcsat/mcsat19.dat
iricore/data/mcsat/mcsat20.dat
iricore/data/mcsat/mcsat21.dat
iricore/data/mcsat/mcsat22.dat
iricore/data/ursi/ursi11.asc
iricore/data/ursi/ursi12.asc
iricore/data/ursi/ursi13.asc
iricore/data/ursi/ursi14.asc
iricore/data/ursi/ursi15.asc
iricore/data/ursi/ursi16.asc
iricore/data/ursi/ursi17.asc
iricore/data/ursi/ursi18.asc
iricore/data/ursi/ursi19.asc
iricore/data/ursi/ursi20.asc
iricore/data/ursi/ursi21.asc
iricore/data/ursi/ursi22.asc
iricore/data_update.py
iricore/iri.py
iricore/iri2016/cira.for
iricore/iri2016/igrf.for
iricore/iri2016/iridreg.for
iricore/iri2016/iriflip.for
iricore/iri2016/irifun.for
iricore/iri2016/irirtam.for
iricore/iri2016/irisub.for
iricore/iri2016/iritec.for
iricore/iri2020/cira.for
iricore/iri2020/igrf.for
iricore-1.9.0.dist-info/LICENSE
iricore-1.9.0.dist-info/METADATA
iricore-1.9.0.dist-info/WHEEL
iricore-1.9.0.dist-info/RECORD
