Metadata-Version: 2.1
Name: iricore
Version: 1.9.0
Summary: A Python wraper to the Inernational Ionosphere Model
Author: Vadym Bidula
Author-email: vadym.bidula@gmail.com
Requires-Python: >=3.9,<4.0
Classifier: Programming Language :: Python :: 3
Classifier: Programming Language :: Python :: 3.9
Classifier: Programming Language :: Python :: 3.10
Classifier: Programming Language :: Python :: 3.11
Classifier: Programming Language :: Python :: 3.12
Classifier: Programming Language :: Python :: 3.13
Requires-Dist: fortranformat (>=2.0.0,<3.0.0)
Requires-Dist: numpy (>=1.25.0,<2.0.0)
Requires-Dist: pymap3d[core] (>=3.0.1,<4.0.0)
